setmlvis/__init__.py
setmlvis/_frontend.py
setmlvis/_version.py
setmlvis/createSetJson.py
setmlvis/widget.py
setmlvis/labextension/.DS_Store
setmlvis/labextension/package.json
setmlvis/labextension/static/568.230765b76337914d6688.js
setmlvis/labextension/static/568.343026abc7ad63214162.js
setmlvis/labextension/static/790.4f47760b6d8559e36679.js
setmlvis/labextension/static/790.4f47760b6d8559e36679.js.LICENSE.txt
setmlvis/labextension/static/790.a7cf482d193ff62560df.js
setmlvis/labextension/static/790.a7cf482d193ff62560df.js.LICENSE.txt
setmlvis/labextension/static/remoteEntry.70f120ed32f339a4531e.js
setmlvis/labextension/static/remoteEntry.8f2fcf2cd9121c0cf948.js
setmlvis/labextension/static/style.js
setmlvis/labextension/static/third-party-licenses.json
setmlvis/nbextension/extension.js
setmlvis/nbextension/index.js
setmlvis-0.5.0.data/data/share/jupyter/labextensions/setmlvis/package.json
setmlvis-0.5.0.data/data/share/jupyter/labextensions/setmlvis/static/568.230765b76337914d6688.js
setmlvis-0.5.0.data/data/share/jupyter/labextensions/setmlvis/static/568.343026abc7ad63214162.js
setmlvis-0.5.0.data/data/share/jupyter/labextensions/setmlvis/static/790.4f47760b6d8559e36679.js
setmlvis-0.5.0.data/data/share/jupyter/labextensions/setmlvis/static/790.4f47760b6d8559e36679.js.LICENSE.txt
setmlvis-0.5.0.data/data/share/jupyter/labextensions/setmlvis/static/790.a7cf482d193ff62560df.js
setmlvis-0.5.0.data/data/share/jupyter/labextensions/setmlvis/static/790.a7cf482d193ff62560df.js.LICENSE.txt
setmlvis-0.5.0.data/data/share/jupyter/labextensions/setmlvis/static/remoteEntry.70f120ed32f339a4531e.js
setmlvis-0.5.0.data/data/share/jupyter/labextensions/setmlvis/static/remoteEntry.8f2fcf2cd9121c0cf948.js
setmlvis-0.5.0.data/data/share/jupyter/labextensions/setmlvis/static/style.js
setmlvis-0.5.0.data/data/share/jupyter/labextensions/setmlvis/static/third-party-licenses.json
setmlvis-0.5.0.data/data/share/jupyter/nbextensions/setmlvis/extension.js
setmlvis-0.5.0.dist-info/METADATA
setmlvis-0.5.0.dist-info/WHEEL
setmlvis-0.5.0.dist-info/licenses/LICENSE.txt
setmlvis-0.5.0.dist-info/RECORD
